[
  {
    "model": "auth.user",
    "pk": 1,
    "fields": {
      "password": "pbkdf2_sha256$870000$aXInhJlTAr5lunGgAmQrco$nfGlVwbR7iwCmST6zN6DiMcFr2Q1lPqKtb6R5JW6RQ8=",
      "last_login": "2024-08-28T13:10:45.047Z",
      "is_superuser": true,
      "username": "admin",
      "first_name": "admin",
      "last_name": "",
      "email": "",
      "is_staff": true,
      "is_active": true,
      "date_joined": "2024-08-28T13:08:04.185Z",
      "groups": [],
      "user_permissions": []
    }
  },
  {
    "model": "auth.user",
    "pk": 2,
    "fields": {
      "password": "pbkdf2_sha256$870000$myL04CWDSiZk7pb437zJtD$cjaBQEt6Pi3a6bHj1RW6IL/N7ERc3f//hUAq+G85D7o=",
      "last_login": "2024-08-28T13:09:46.659Z",
      "is_superuser": false,
      "username": "staff",
      "first_name": "staff",
      "last_name": "",
      "email": "",
      "is_staff": true,
      "is_active": true,
      "date_joined": "2024-08-28T13:09:46.482Z",
      "groups": [],
      "user_permissions": []
    }
  },
  {
    "model": "auth.user",
    "pk": 3,
    "fields": {
      "password": "pbkdf2_sha256$870000$nRkUZfdBnhFPdAOuwWIpty$01rAZ01STTIvOVW58UTvm6CL+/HLjrn2cqGOYFUZzTA=",
      "last_login": null,
      "is_superuser": false,
      "username": "user",
      "first_name": "",
      "last_name": "",
      "email": "",
      "is_staff": false,
      "is_active": true,
      "date_joined": "2024-08-28T13:11:01.184Z",
      "groups": [],
      "user_permissions": []
    }
  },
  {
    "model": "user_profile.profile",
    "pk": 1,
    "fields": {
      "user": 1,
      "full_name": "admin",
      "unique_email": "admin@mail.ru",
      "unique_phone": "+79214334422"
    }
  },
  {
    "model": "user_profile.profile",
    "pk": 2,
    "fields": {
      "user": 2,
      "full_name": "staff",
      "unique_email": "staff@mail.ru",
      "unique_phone": "+79215554433"
    }
  },
  {
    "model": "user_profile.profile",
    "pk": 3,
    "fields": {
      "user": 3,
      "full_name": "user full name",
      "unique_email": "user@mail.ru",
      "unique_phone": "+79118886633"
    }
  },
  {
    "model": "user_profile.avatar",
    "pk": 1,
    "fields": {
      "profile": 1,
      "src": "users/user_1/avatar/1.jpg",
      "alt": "Your '1.jpg' is currently unavailable!"
    }
  },
  {
    "model": "user_profile.avatar",
    "pk": 2,
    "fields": {
      "profile": 2,
      "src": "users/user_2/avatar/arto-marttinen-fHXP17AxOEk-unsplash.jpg",
      "alt": "Your 'arto-marttinen-fHXP17AxOEk-unsplash.jpg' is currently unavailable!"
    }
  },
  {
    "model": "user_profile.avatar",
    "pk": 3,
    "fields": {
      "profile": 3,
      "src": "users/user_3/avatar/2.jpg",
      "alt": "Your '2.jpg' is currently unavailable!"
    }
  }
]